risc_processor.srcs/sim_1/new/alu.v
`timescale 1ns / 1ps
module alu(
    input [31:0] a,
    input [31:0] b,
    input [3:0] alu_ctrl,
    output reg [31:0] result,
    output zero
);
    assign zero = (result == 32'b0);
    always @(*) begin
        case (alu_ctrl)
            4'b0000: result = a + b; // ADD
            4'b0001: result = a - b; // SUB
            4'b0010: result = (a < b) ? 32'b1 : 32'b0; // SLT
            4'b0011: result = ($signed(a) < $signed(b)) ? 32'b1 : 32'b0; // SLT signed
            4'b0100: result = a & b; // AND
            4'b0101: result = a | b; // OR
            4'b0110: result = a ^ b; // XOR
            4'b0111: result = a << b[4:0]; // SLL
            4'b1000: result = a >> b[4:0]; // SRL logical
            4'b1001: result = $signed(a) >>> b[4:0]; // SRA arithmetic
            default: result = 32'b0;
        endcase
    end
endmodule

risc_processor.srcs/sim_1/new/forwarding_unit.v
`timescale 1ns / 1ps
// Determine forwarding to EX stage operands
module forwarding_unit(
    input [4:0] ex_rs1,
    input [4:0] ex_rs2,
    input [4:0] mem_rd,
    input mem_reg_write,
    input [4:0] wb_rd,
    input wb_reg_write,
    output reg [1:0] forwardA, // 00 = from reg, 10 = from MEM, 01 = from WB
    output reg [1:0] forwardB
);
    always @(*) begin
        // default
        forwardA = 2'b00;
        forwardB = 2'b00;

        // EX hazard: MEM stage
        if (mem_reg_write && (mem_rd != 0) && (mem_rd == ex_rs1)) forwardA = 2'b10;
        if (mem_reg_write && (mem_rd != 0) && (mem_rd == ex_rs2)) forwardB = 2'b10;

        // WB hazard: WB stage
        if (wb_reg_write && (wb_rd != 0) && !(mem_reg_write && (mem_rd != 0) && (mem_rd == ex_rs1)) && (wb_rd == ex_rs1)) forwardA = 2'b01;
        if (wb_reg_write && (wb_rd != 0) && !(mem_reg_write && (mem_rd != 0) && (mem_rd == ex_rs2)) && (wb_rd == ex_rs2)) forwardB = 2'b01;
    end
endmodule

risc_processor.srcs/sim_1/new/hazard_unit.v
`timescale 1ns / 1ps
// Detect load-use hazard and stall; simple
module hazard_unit(
    input [4:0] id_rs1,
    input [4:0] id_rs2,
    input [4:0] ex_rd,
    input ex_mem_read,
    output reg stall,
    output reg pc_write,
    output reg if_id_write
);
    always @(*) begin
        // default: no stall
        stall = 0;
        pc_write = 1;
        if_id_write = 1;

        // load-use hazard: if EX is a load and its rd matches ID rs1/rs2, stall one cycle
        if (ex_mem_read && (ex_rd != 0) && ((ex_rd == id_rs1) || (ex_rd == id_rs2))) begin
            stall = 1;
            pc_write = 0;
            if_id_write = 0;
        end
    end
endmodule

risc_processor.srcs/sim_1/new/data_mem.v
`timescale 1ns / 1ps
// Simple data memory (byte-addressable) with word reads/writes (aligned)
module data_mem(
    input clk,
    input mem_write,
    input mem_read,
    input [31:0] addr,
    input [31:0] write_data,
    output reg [31:0] read_data
);
    reg [7:0] dmem [0:4095]; // 4KB
    integer i;
    initial begin
        for (i=0;i<4096;i=i+1) dmem[i]=8'b0;
    end

    always @(posedge clk) begin
        if (mem_write) begin
            // store word (little endian)
            dmem[addr + 0] <= write_data[7:0];
            dmem[addr + 1] <= write_data[15:8];
            dmem[addr + 2] <= write_data[23:16];
            dmem[addr + 3] <= write_data[31:24];
        end
    end

    always @(*) begin
        if (mem_read) begin
            read_data = {dmem[addr+3], dmem[addr+2], dmem[addr+1], dmem[addr+0]};
        end else read_data = 32'b0;
    end
endmodule

risc_processor.srcs/sim_1/new/regfile.v
`timescale 1ns / 1ps
//////////////////////////////////////////////////////////////////////////////////
// Company: 
// Engineer: 
// 
// Create Date: 17.11.2025 23:40:33
// Design Name: 
// Module Name: regfile
// Project Name: 
// Target Devices: 
// Tool Versions: 
// Description: 
// 
// Dependencies: 
// 
// Revision:
// Revision 0.01 - File Created
// Additional Comments:
// 
//////////////////////////////////////////////////////////////////////////////////


// 32x32 register file, x0 hardwired to 0
module regfile(
    input clk,
    input we,
    input [4:0] ra1,
    input [4:0] ra2,
    input [4:0] wa,
    input [31:0] wd,
    output [31:0] rd1,
    output [31:0] rd2
);
    reg [31:0] regs [0:31];
    integer i;
    initial begin
        for (i=0;i<32;i=i+1) regs[i]=32'b0;
    end

    // read
    assign rd1 = (ra1==0)? 32'b0 : regs[ra1];
    assign rd2 = (ra2==0)? 32'b0 : regs[ra2];

    // write (on posedge)
    always @(posedge clk) begin
        if (we && wa != 0) regs[wa] <= wd;
    end
endmodule

risc_processor.srcs/sim_1/new/defines.v
`timescale 1ns / 1ps
//////////////////////////////////////////////////////////////////////////////////
// Company: 
// Engineer: 
// 
// Create Date: 17.11.2025 23:37:18
// Design Name: 
// Module Name: defines
// Project Name: 
// Target Devices: 
// Tool Versions: 
// Description: 
// 
// Dependencies: 
// 
// Revision:
// Revision 0.01 - File Created
// Additional Comments:
// 
//////////////////////////////////////////////////////////////////////////////////


// Simple RISC-V field defines
`ifndef DEFINES_V
`define DEFINES_V

// Opcodes
`define OP_R    7'b0110011
`define OP_I    7'b0010011
`define OP_LOAD 7'b0000011
`define OP_STORE 7'b0100011
`define OP_BRANCH 7'b1100011
`define OP_LUI 7'b0110111
`define OP_AUIPC 7'b0010111
`define OP_JAL 7'b1101111
`define OP_JALR 7'b1100111
`define OP_SYSTEM 7'b1110011

`endif

risc_processor.srcs/sim_1/new/control.v
`timescale 1ns / 1ps
`include "defines.v"
module control_unit(
    input [6:0] opcode,
    input [2:0] funct3,
    input [6:0] funct7,
    output reg reg_write,
    output reg mem_read,
    output reg mem_write,
    output reg branch,
    output reg [1:0] alu_src, // 0 = reg, 1 = imm (I), 2 = imm (S), 3 = imm (U/J)
    output reg mem_to_reg,
    output reg [3:0] alu_op, // internal ALU control better resolved in ALU control
    output reg jal,
    output reg jalr
);
    always @(*) begin
        // defaults
        reg_write = 0;
        mem_read = 0;
        mem_write = 0;
        branch = 0;
        alu_src = 0;
        mem_to_reg = 0;
        alu_op = 4'b0000;
        jal = 0;
        jalr = 0;

        case (opcode)
            `OP_R: begin
                reg_write = 1;
                alu_src = 0;
                // determine ALU op from funct3/funct7 later in ALU control unit, but we'll approximate
                // We'll pass full funct fields to EX stage; for simplicity map to add/sub/slt/and/or
                if (funct3 == 3'b000 && funct7 == 7'b0100000) alu_op = 4'b0001; // SUB
                else if (funct3 == 3'b000) alu_op = 4'b0000; // ADD
                else if (funct3 == 3'b010) alu_op = 4'b0010; // SLT
                else if (funct3 == 3'b111) alu_op = 4'b0100; // AND
                else if (funct3 == 3'b110) alu_op = 4'b0101; // OR
                else if (funct3 == 3'b100) alu_op = 4'b0110; // XOR
                else if (funct3 == 3'b001) alu_op = 4'b0111; // SLL
                else if (funct3 == 3'b101 && funct7 == 7'b0100000) alu_op = 4'b1001; // SRA
                else if (funct3 == 3'b101) alu_op = 4'b1000; // SRL
            end
            `OP_I: begin
                reg_write = 1;
                alu_src = 1;
                // approximate: ADDI and other immediate ops
                if (funct3 == 3'b000) alu_op = 4'b0000; // ADDI
                else if (funct3 == 3'b010) alu_op = 4'b0010; // SLTI
                else if (funct3 == 3'b111) alu_op = 4'b0100; // ANDI
                else if (funct3 == 3'b110) alu_op = 4'b0101; // ORI
            end
            `OP_LOAD: begin
                reg_write = 1;
                mem_read = 1;
                mem_to_reg = 1;
                alu_src = 1;
                alu_op = 4'b0000; // ADD for address calc
            end
            `OP_STORE: begin
                mem_write = 1;
                alu_src = 2; // S-type immediate
                alu_op = 4'b0000; // ADD for address calc
            end
            `OP_BRANCH: begin
                branch = 1;
                alu_src = 0;
                alu_op = 4'b0001; // SUB to compare
            end
            `OP_LUI: begin
                reg_write = 1;
                alu_src = 3;
                alu_op = 4'b0000;
            end
            `OP_AUIPC: begin
                reg_write = 1;
                alu_src = 3;
                alu_op = 4'b0000;
            end
            `OP_JAL: begin
                reg_write = 1;
                jal = 1;
                alu_src = 0;
            end
            `OP_JALR: begin
                reg_write = 1;
                jalr = 1;
                alu_src = 1;
            end
            default: begin end
        endcase
    end
endmodule

risc_processor.srcs/sim_1/new/imm_gen.v
`timescale 1ns / 1ps
// Immediate generator for various instruction formats
module imm_gen(
    input [31:0] instr,
    output reg [31:0] imm_i,
    output reg [31:0] imm_s,
    output reg [31:0] imm_b,
    output reg [31:0] imm_u,
    output reg [31:0] imm_j
);
    always @(*) begin
        // I-type
        imm_i = {{20{instr[31]}}, instr[31:20]};

        // S-type
        imm_s = {{20{instr[31]}}, instr[31:25], instr[11:7]};

        // B-type (branch) imm = sign<<12 | bit11 << 11 | bits[10:5] << 5 | bits[4:1]<<1
        imm_b = {{19{instr[31]}}, instr[31], instr[7], instr[30:25], instr[11:8], 1'b0};

        // U-type
        imm_u = {instr[31:12], 12'b0};

        // J-type
        imm_j = {{11{instr[31]}}, instr[31], instr[19:12], instr[20], instr[30:21], 1'b0};
    end
endmodule

risc_processor.srcs/sim_1/new/instr_mem.v
`timescale 1ns / 1ps
// Simple instruction memory, word addressed by PC>>2, size 1024 words (4KB)
module instr_mem(
    input [31:0] addr,
    output [31:0] instr
);
    reg [31:0] imem [0:1023];
    initial begin
        // read instruction memory file (hex). Provide program.mem in project.
        $readmemh("program.mem", imem);
    end
    assign instr = imem[addr[11:2]]; // word addressed
endmodule

risc_processor.srcs/sources_1/new/risc_processor.v
`timescale 1ns / 1ps

//////////////////////////////////////////////////////////////////////////////////
// Company: 
// Engineer: 
// 
// Create Date: 17.11.2025 23:35:15
// Design Name: 
// Module Name: risc_processor
// Project Name: 
// Target Devices: 
// Tool Versions: 
// Description: 
// 
// Dependencies: 
// 
// Revision:
// Revision 0.01 - File Created
// Additional Comments:
// 
//////////////////////////////////////////////////////////////////////////////////

`define OP_R    7'b0110011
`define OP_I    7'b0010011
`define OP_LOAD 7'b0000011
`define OP_STORE 7'b0100011
`define OP_BRANCH 7'b1100011
`define OP_LUI 7'b0110111
`define OP_AUIPC 7'b0010111
`define OP_JAL 7'b1101111
`define OP_JALR 7'b1100111
`define OP_SYSTEM 7'b1110011
module risc_processor(
    input clk,
    input reset
);
    // Program Counter
    reg [31:0] pc;
    wire [31:0] instr_if;

    // Instruction memory
    instr_mem imem(.addr(pc), .instr(instr_if));

    // IF/ID pipeline register
    reg [31:0] if_id_pc;
    reg [31:0] if_id_instr;

    // ID signals
    wire [6:0] id_opcode = if_id_instr[6:0];
    wire [4:0] id_rs1 = if_id_instr[19:15];
    wire [4:0] id_rs2 = if_id_instr[24:20];
    wire [4:0] id_rd  = if_id_instr[11:7];
    wire [2:0] id_funct3 = if_id_instr[14:12];
    wire [6:0] id_funct7 = if_id_instr[31:25];

    // imm gen
    wire [31:0] id_imm_i, id_imm_s, id_imm_b, id_imm_u, id_imm_j;
    imm_gen ig(.instr(if_id_instr), .imm_i(id_imm_i), .imm_s(id_imm_s), .imm_b(id_imm_b), .imm_u(id_imm_u), .imm_j(id_imm_j));

    // control
    wire id_reg_write, id_mem_read, id_mem_write, id_branch, id_mem_to_reg, id_jal, id_jalr;
    wire [1:0] id_alu_src;
    wire [3:0] id_alu_op;
    control_unit cu(.opcode(id_opcode), .funct3(id_funct3), .funct7(id_funct7),
                    .reg_write(id_reg_write), .mem_read(id_mem_read), .mem_write(id_mem_write),
                    .branch(id_branch), .alu_src(id_alu_src), .mem_to_reg(id_mem_to_reg),
                    .alu_op(id_alu_op), .jal(id_jal), .jalr(id_jalr));

    // Register file (single instance with writeback control)
    reg wb_we;
    reg [4:0] wb_wa;
    reg [31:0] wb_wd;
    wire [31:0] rf_rd1, rf_rd2;

    regfile rf(.clk(clk), .we(wb_we), .ra1(id_rs1), .ra2(id_rs2), .wa(wb_wa), .wd(wb_wd), .rd1(rf_rd1), .rd2(rf_rd2));

    // ID/EX pipeline registers
    reg [31:0] id_ex_pc;
    reg [31:0] id_ex_rd1, id_ex_rd2;
    reg [31:0] id_ex_imm;
    reg [4:0] id_ex_rs1, id_ex_rs2, id_ex_rd;
    reg [6:0] id_ex_opcode;
    reg [2:0] id_ex_funct3;
    reg [6:0] id_ex_funct7;
    reg id_ex_reg_write, id_ex_mem_read, id_ex_mem_write, id_ex_branch, id_ex_mem_to_reg, id_ex_jal, id_ex_jalr;
    reg [1:0] id_ex_alu_src;
    reg [3:0] id_ex_alu_op;

    // EX stage signals
    wire [31:0] ex_alu_result;
    wire ex_zero;

    // Forwarding unit inputs
    wire [4:0] ex_rs1 = id_ex_rs1;
    wire [4:0] ex_rs2 = id_ex_rs2;

    // EX/MEM pipeline
    reg [31:0] ex_mem_alu_result;
    reg [31:0] ex_mem_write_data;
    reg [4:0] ex_mem_rd;
    reg ex_mem_reg_write, ex_mem_mem_read, ex_mem_mem_write, ex_mem_mem_to_reg;
    reg [31:0] ex_mem_pc;

    // MEM/WB pipeline
    reg [31:0] mem_wb_read_data;
    reg [31:0] mem_wb_alu_result;
    reg [4:0] mem_wb_rd;
    reg mem_wb_reg_write, mem_wb_mem_to_reg;

    // data memory
    wire [31:0] mem_read_data;
    data_mem dmem(.clk(clk), .mem_write(ex_mem_mem_write), .mem_read(ex_mem_mem_read),
                  .addr(ex_mem_alu_result), .write_data(ex_mem_write_data), .read_data(mem_read_data));

    // Hazard detection unit
    wire stall, pc_write, if_id_write;
    hazard_unit hz(.id_rs1(id_rs1), .id_rs2(id_rs2), .ex_rd(id_ex_rd), .ex_mem_read(id_ex_mem_read), .stall(stall), .pc_write(pc_write), .if_id_write(if_id_write));

    // Forwarding unit
    wire [1:0] forwardA, forwardB;
    forwarding_unit fu(.ex_rs1(ex_rs1), .ex_rs2(ex_rs2),
                       .mem_rd(ex_mem_rd), .mem_reg_write(ex_mem_reg_write),
                       .wb_rd(mem_wb_rd), .wb_reg_write(mem_wb_reg_write),
                       .forwardA(forwardA), .forwardB(forwardB));

    // ALU control and inputs
    // We'll use id_ex_alu_op to select operation; if more refinement needed use funct fields
    reg [3:0] alu_ctrl;
    always @(*) alu_ctrl = id_ex_alu_op;

    // ALU operand A: forwarded or from id_ex_rd1
    reg [31:0] alu_a;
    reg [31:0] alu_b;

    // ALU instance
    alu alu0(.a(alu_a), .b(alu_b), .alu_ctrl(alu_ctrl), .result(ex_alu_result), .zero(ex_zero));

    // PC update logic (simple): PC + 4, branches resolved in EX (compute branch target and take)
    wire [31:0] pc_plus4 = pc + 4;

    // Pipeline registers behavior
    integer i;
    reg [31:0] b_from_reg;
    // Reset and sequential pipeline update
    always @(posedge clk or posedge reset) begin
        if (reset) begin
            pc <= 0;
            if_id_pc <= 0;
            if_id_instr <= 32'b0;
            // flush pipeline regs
            id_ex_pc <= 0;
            id_ex_rd1 <= 0; id_ex_rd2 <= 0; id_ex_imm <= 0;
            id_ex_rs1 <= 0; id_ex_rs2 <= 0; id_ex_rd <= 0;
            id_ex_opcode <= 0; id_ex_funct3 <= 0; id_ex_funct7 <= 0;
            id_ex_reg_write <= 0; id_ex_mem_read <= 0; id_ex_mem_write <= 0; id_ex_branch <= 0; id_ex_mem_to_reg <= 0;
            id_ex_alu_src <= 0; id_ex_alu_op <= 0; id_ex_jal <= 0; id_ex_jalr <= 0;
            ex_mem_alu_result <= 0; ex_mem_write_data <= 0; ex_mem_rd <= 0;
            ex_mem_reg_write <= 0; ex_mem_mem_read <= 0; ex_mem_mem_write <= 0; ex_mem_mem_to_reg <= 0;
            mem_wb_read_data <= 0; mem_wb_alu_result <= 0; mem_wb_rd <= 0; mem_wb_reg_write <= 0; mem_wb_mem_to_reg <= 0;
            // regfile write control
            wb_we <= 0; wb_wa <= 0; wb_wd <= 0;
        end else begin
            // IF stage - update PC
            if (pc_write) pc <= pc_plus4;

            // IF/ID pipeline (with stall control)
            if (if_id_write) begin
                if_id_pc <= pc;
                if_id_instr <= instr_if;
            end else if (stall) begin
                // keep if_id registers unchanged to stall
                if_id_pc <= if_id_pc;
                if_id_instr <= if_id_instr;
            end

            // ID/EX pipeline update (if stall, insert bubble)
            if (stall) begin
                // insert bubble: clear control signals
                id_ex_pc <= 0;
                id_ex_rd1 <= 0; id_ex_rd2 <= 0; id_ex_imm <= 0;
                id_ex_rs1 <= 0; id_ex_rs2 <= 0; id_ex_rd <= 0;
                id_ex_opcode <= 0; id_ex_funct3 <= 0; id_ex_funct7 <= 0;
                id_ex_reg_write <= 0; id_ex_mem_read <= 0; id_ex_mem_write <= 0; id_ex_branch <= 0; id_ex_mem_to_reg <= 0;
                id_ex_alu_src <= 0; id_ex_alu_op <= 0; id_ex_jal <= 0; id_ex_jalr <= 0;
            end else begin
                id_ex_pc <= if_id_pc;
                id_ex_rd1 <= rf_rd1;
                id_ex_rd2 <= rf_rd2;
                // Choose immediate according to alu_src: we'll store selected imm in id_ex_imm
                case (id_alu_src)
                    2'b00: id_ex_imm <= 32'b0;
                    2'b01: id_ex_imm <= id_imm_i;
                    2'b10: id_ex_imm <= id_imm_s;
                    2'b11: id_ex_imm <= id_imm_u; // used for LUI/AUIPC (approx)
                    default: id_ex_imm <= 32'b0;
                endcase
                id_ex_rs1 <= id_rs1;
                id_ex_rs2 <= id_rs2;
                id_ex_rd <= id_rd;
                id_ex_opcode <= id_opcode;
                id_ex_funct3 <= id_funct3;
                id_ex_funct7 <= id_funct7;
                id_ex_reg_write <= id_reg_write;
                id_ex_mem_read <= id_mem_read;
                id_ex_mem_write <= id_mem_write;
                id_ex_branch <= id_branch;
                id_ex_mem_to_reg <= id_mem_to_reg;
                id_ex_alu_src <= id_alu_src;
                id_ex_alu_op <= id_alu_op;
                id_ex_jal <= id_jal;
                id_ex_jalr <= id_jalr;
            end

            // EX stage: compute ALU inputs with forwarding
            // forwarding mux for A
            case (forwardA)
                2'b00: alu_a <= id_ex_rd1;
                2'b10: alu_a <= ex_mem_alu_result;
                2'b01: alu_a <= (mem_wb_mem_to_reg ? mem_wb_read_data : mem_wb_alu_result);
                default: alu_a <= id_ex_rd1;
            endcase

            // B input depends on alu_src: choose imm or forwarded register data
            case (forwardB)
                2'b00: b_from_reg <= id_ex_rd2;
                2'b10: b_from_reg <= ex_mem_alu_result;
                2'b01: b_from_reg <= (mem_wb_mem_to_reg ? mem_wb_read_data : mem_wb_alu_result);
                default: b_from_reg <= id_ex_rd2;
            endcase

            if (id_ex_alu_src == 2'b00)
                alu_b <= b_from_reg;
            else if (id_ex_alu_src == 2'b01 || id_ex_alu_src == 2'b10)
                alu_b <= id_ex_imm;
            else if (id_ex_alu_src == 2'b11)
                alu_b <= id_ex_imm;

            // EX/MEM pipeline update
            ex_mem_alu_result <= ex_alu_result;
            ex_mem_write_data <= b_from_reg;
            ex_mem_rd <= id_ex_rd;
            ex_mem_reg_write <= id_ex_reg_write;
            ex_mem_mem_read <= id_ex_mem_read;
            ex_mem_mem_write <= id_ex_mem_write;
            ex_mem_mem_to_reg <= id_ex_mem_to_reg;
            ex_mem_pc <= id_ex_pc;

            // MEM stage: data memory access already done combinationally via dmem outputs
            // Capture memory output into pipeline
            mem_wb_read_data <= mem_read_data;
            mem_wb_alu_result <= ex_mem_alu_result;
            mem_wb_rd <= ex_mem_rd;
            mem_wb_reg_write <= ex_mem_reg_write;
            mem_wb_mem_to_reg <= ex_mem_mem_to_reg;

            // WB stage: perform write-back to register file
            wb_we <= mem_wb_reg_write;
            wb_wa <= mem_wb_rd;
            wb_wd <= (mem_wb_mem_to_reg ? mem_wb_read_data : mem_wb_alu_result);
        end
    end
endmodule

risc_processor.srcs/sim_1/new/tb_riscv.v
`timescale 1ns/1ps
module tb_riscv;
    reg clk;
    reg reset;

    // instantiate core
    risc_processor core(.clk(clk), .reset(reset));

    // clock
    initial begin
        clk = 0;
        forever #5 clk = ~clk; // 100 MHz ~ 10ns period; here 10ns period -> 100MHz
    end

    initial begin
        reset = 1;
        #20;
        reset = 0;
        // run some cycles
        #2000;
        $display("Simulation done");
        $finish;
    end

    // optional waveform
    initial begin
        $dumpfile("riscv.vcd");
        $dumpvars(0, tb_riscv);
    end
endmodule

risc_processor.sim/sim_1/behav/xsim/riscv.vcd
$date
   Tue Nov 18 00:18:48 2025
$end

$version
  2025.1.0
  $dumpfile ("riscv.vcd") 
$end

$timescale
  1ps
$end

$scope module tb_riscv $end
$var reg 1 ! clk $end
$var reg 1 " reset $end
$scope module core $end
$var wire 1 # clk $end
$var wire 1 $ reset $end
$var reg 32 % pc [31:0] $end
$var wire 32 & instr_if [31:0] $end
$var reg 32 ' if_id_pc [31:0] $end
$var reg 32 ( if_id_instr [31:0] $end
$var wire 7 ) id_opcode [6:0] $end
$var wire 5 * id_rs1 [4:0] $end
$var wire 5 + id_rs2 [4:0] $end
$var wire 5 , id_rd [4:0] $end
$var wire 3 - id_funct3 [2:0] $end
$var wire 7 . id_funct7 [6:0] $end
$var wire 32 / id_imm_i [31:0] $end
$var wire 32 0 id_imm_s [31:0] $end
$var wire 32 1 id_imm_b [31:0] $end
$var wire 32 2 id_imm_u [31:0] $end
$var wire 32 3 id_imm_j [31:0] $end
$var wire 1 4 id_reg_write $end
$var wire 1 5 id_mem_read $end
$var wire 1 6 id_mem_write $end
$var wire 1 7 id_branch $end
$var wire 1 8 id_mem_to_reg $end
$var wire 1 9 id_jal $end
$var wire 1 : id_jalr $end
$var wire 2 ; id_alu_src [1:0] $end
$var wire 4 < id_alu_op [3:0] $end
$var reg 1 = wb_we $end
$var reg 5 > wb_wa [4:0] $end
$var reg 32 ? wb_wd [31:0] $end
$var wire 32 @ rf_rd1 [31:0] $end
$var wire 32 A rf_rd2 [31:0] $end
$var reg 32 B id_ex_pc [31:0] $end
$var reg 32 C id_ex_rd1 [31:0] $end
$var reg 32 D id_ex_rd2 [31:0] $end
$var reg 32 E id_ex_imm [31:0] $end
$var reg 5 F id_ex_rs1 [4:0] $end
$var reg 5 G id_ex_rs2 [4:0] $end
$var reg 5 H id_ex_rd [4:0] $end
$var reg 7 I id_ex_opcode [6:0] $end
$var reg 3 J id_ex_funct3 [2:0] $end
$var reg 7 K id_ex_funct7 [6:0] $end
$var reg 1 L id_ex_reg_write $end
$var reg 1 M id_ex_mem_read $end
$var reg 1 N id_ex_mem_write $end
$var reg 1 O id_ex_branch $end
$var reg 1 P id_ex_mem_to_reg $end
$var reg 1 Q id_ex_jal $end
$var reg 1 R id_ex_jalr $end
$var reg 2 S id_ex_alu_src [1:0] $end
$var reg 4 T id_ex_alu_op [3:0] $end
$var wire 32 U ex_alu_result [31:0] $end
$var wire 1 V ex_zero $end
$var wire 5 W ex_rs1 [4:0] $end
$var wire 5 X ex_rs2 [4:0] $end
$var reg 32 Y ex_mem_alu_result [31:0] $end
$var reg 32 Z ex_mem_write_data [31:0] $end
$var reg 5 [ ex_mem_rd [4:0] $end
$var reg 1 \ ex_mem_reg_write $end
$var reg 1 ] ex_mem_mem_read $end
$var reg 1 ^ ex_mem_mem_write $end
$var reg 1 _ ex_mem_mem_to_reg $end
$var reg 32 ` ex_mem_pc [31:0] $end
$var reg 32 a mem_wb_read_data [31:0] $end
$var reg 32 b mem_wb_alu_result [31:0] $end
$var reg 5 c mem_wb_rd [4:0] $end
$var reg 1 d mem_wb_reg_write $end
$var reg 1 e mem_wb_mem_to_reg $end
$var wire 32 f mem_read_data [31:0] $end
$var wire 1 g stall $end
$var wire 1 h pc_write $end
$var wire 1 i if_id_write $end
$var wire 2 j forwardA [1:0] $end
$var wire 2 k forwardB [1:0] $end
$var reg 4 l alu_ctrl [3:0] $end
$var reg 32 m alu_a [31:0] $end
$var reg 32 n alu_b [31:0] $end
$var wire 32 o pc_plus4 [31:0] $end
$var integer 32 p i [31:0] $end
$var reg 32 q b_from_reg [31:0] $end
$scope module imem $end
$var wire 32 r addr [31:0] $end
$var wire 32 & instr [31:0] $end
$upscope $end
$scope module ig $end
$var wire 32 s instr [31:0] $end
$var reg 32 t imm_i [31:0] $end
$var reg 32 u imm_s [31:0] $end
$var reg 32 v imm_b [31:0] $end
$var reg 32 w imm_u [31:0] $end
$var reg 32 x imm_j [31:0] $end
$upscope $end
$scope module cu $end
$var wire 7 ) opcode [6:0] $end
$var wire 3 - funct3 [2:0] $end
$var wire 7 . funct7 [6:0] $end
$var reg 1 y reg_write $end
$var reg 1 z mem_read $end
$var reg 1 { mem_write $end
$var reg 1 | branch $end
$var reg 2 } alu_src [1:0] $end
$var reg 1 ~ mem_to_reg $end
$var reg 4 !! alu_op [3:0] $end
$var reg 1 "! jal $end
$var reg 1 #! jalr $end
$upscope $end
$scope module rf $end
$var wire 1 # clk $end
$var wire 1 $! we $end
$var wire 5 * ra1 [4:0] $end
$var wire 5 + ra2 [4:0] $end
$var wire 5 %! wa [4:0] $end
$var wire 32 &! wd [31:0] $end
$var wire 32 @ rd1 [31:0] $end
$var wire 32 A rd2 [31:0] $end
$var integer 32 '! i [31:0] $end
$upscope $end
$scope module dmem $end
$var wire 1 # clk $end
$var wire 1 (! mem_write $end
$var wire 1 )! mem_read $end
$var wire 32 *! addr [31:0] $end
$var wire 32 +! write_data [31:0] $end
$var reg 32 ,! read_data [31:0] $end
$var integer 32 -! i [31:0] $end
$upscope $end
$scope module hz $end
$var wire 5 * id_rs1 [4:0] $end
$var wire 5 + id_rs2 [4:0] $end
$var wire 5 .! ex_rd [4:0] $end
$var wire 1 /! ex_mem_read $end
$var reg 1 0! stall $end
$var reg 1 1! pc_write $end
$var reg 1 2! if_id_write $end
$upscope $end
$scope module fu $end
$var wire 5 W ex_rs1 [4:0] $end
$var wire 5 X ex_rs2 [4:0] $end
$var wire 5 3! mem_rd [4:0] $end
$var wire 1 4! mem_reg_write $end
$var wire 5 5! wb_rd [4:0] $end
$var wire 1 6! wb_reg_write $end
$var reg 2 7! forwardA [1:0] $end
$var reg 2 8! forwardB [1:0] $end
$upscope $end
$scope module alu0 $end
$var wire 32 9! a [31:0] $end
$var wire 32 :! b [31:0] $end
$var wire 4 ;! alu_ctrl [3:0] $end
$var reg 32 <! result [31:0] $end
$var wire 1 V zero $end
$upscope $end
$upscope $end
$upscope $end
$enddefinitions $end

#0
$dumpvars
0!
b0 !!
1"
0"!
0#
0#!
1$
0$!
b0 %
b0 %!
bx &
b0 &!
b0 '
b100000 '!
b0 (
0(!
b0 )
0)!
b0 *
b0 *!
b0 +
b0 +!
b0 ,
b0 ,!
b0 -
b1000000000000 -!
b0 .
b0 .!
b0 /
0/!
b0 0
00!
b0 1
11!
b0 2
12!
b0 3
b0 3!
04
04!
05
b0 5!
06
06!
07
b0 7!
08
b0 8!
09
bx 9!
0:
bx :!
b0 ;
b0 ;!
b0 <
bx <!
0=
b0 >
b0 ?
b0 @
b0 A
b0 B
b0 C
b0 D
b0 E
b0 F
b0 G
b0 H
b0 I
b0 J
b0 K
0L
0M
0N
0O
0P
0Q
0R
b0 S
b0 T
bx U
xV
b0 W
b0 X
b0 Y
b0 Z
b0 [
0\
0]
0^
0_
bx `
b0 a
b0 b
b0 c
0d
0e
b0 f
0g
1h
1i
b0 j
b0 k
b0 l
bx m
bx n
b100 o
bx p
bx q
b0 r
b0 s
b0 t
b0 u
b0 v
b0 w
b0 x
0y
0z
0{
0|
b0 }
0~
$end

#5000
1!
1#

#10000
0!
0#

#15000
1!
1#

#20000
0!
0"
0#
0$

#25000
1!
1#
b100 %
bx (
bx )
bx *
bx *!
bx +
bx +!
bx ,
bx -
bx .
bx /
bx 0
bx0 1
bx000000000000 2
bx0 3
b0 9!
bx @
bx A
bx Y
bx Z
b0 `
b0 m
b1000 o
b0 q
b100 r
bx s
bx t
bx u
bx0 v
bx000000000000 w
bx0 x

#30000
0!
0#

#35000
1!
1#
b1000 %
b100 '
b0 +!
bx .!
b0 :!
b0 <!
bx C
bx D
bx F
bx G
bx H
bx I
bx J
bx K
b0 U
1V
bx W
bx X
b0 Z
bx b
b0 n
b1100 o
b1000 r

#40000
0!
0#

#45000
1!
1#
b1100 %
bx &!
b1000 '
b0 *!
bx 3!
bx 9!
bx <!
bx ?
b100 B
bx U
xV
b0 Y
bx [
bx m
b10000 o
bx q
b1100 r

#50000
0!
0#

#55000
1!
1#
b10000 %
b1100 '
bx *!
bx +!
bx 5!
bx :!
b1000 B
bx Y
bx Z
b100 `
b0 b
bx c
bx n
b10100 o
b10000 r

#60000
0!
0#

#65000
1!
1#
b10100 %
bx %!
b0 &!
b10000 '
bx >
b0 ?
b1100 B
b1000 `
bx b
b11000 o
b10100 r

#70000
0!
0#

#75000
1!
1#
b11000 %
bx &!
b10100 '
bx ?
b10000 B
b1100 `
b11100 o
b11000 r

#80000
0!
0#

#85000
1!
1#
b11100 %
b11000 '
b10100 B
b10000 `
b100000 o
b11100 r

#90000
0!
0#

#95000
1!
1#
b100000 %
b11100 '
b11000 B
b10100 `
b100100 o
b100000 r

#100000
0!
0#

#105000
1!
1#
b100100 %
b100000 '
b11100 B
b11000 `
b101000 o
b100100 r

#110000
0!
0#

#115000
1!
1#
b101000 %
b100100 '
b100000 B
b11100 `
b101100 o
b101000 r

#120000
0!
0#

#125000
1!
1#
b101100 %
b101000 '
b100100 B
b100000 `
b110000 o
b101100 r

#130000
0!
0#

#135000
1!
1#
b110000 %
b101100 '
b101000 B
b100100 `
b110100 o
b110000 r

#140000
0!
0#

#145000
1!
1#
b110100 %
b110000 '
b101100 B
b101000 `
b111000 o
b110100 r

#150000
0!
0#

#155000
1!
1#
b111000 %
b110100 '
b110000 B
b101100 `
b111100 o
b111000 r

#160000
0!
0#

#165000
1!
1#
b111100 %
b111000 '
b110100 B
b110000 `
b1000000 o
b111100 r

#170000
0!
0#

#175000
1!
1#
b1000000 %
b111100 '
b111000 B
b110100 `
b1000100 o
b1000000 r

#180000
0!
0#

#185000
1!
1#
b1000100 %
b1000000 '
b111100 B
b111000 `
b1001000 o
b1000100 r

#190000
0!
0#

#195000
1!
1#
b1001000 %
b1000100 '
b1000000 B
b111100 `
b1001100 o
b1001000 r

#200000
0!
0#

